{
  "count": 10,
  "page": 2,
  "per_page": 50,
  "results": [
    {
      "updated_at": "1987-05-08T22:00:00.0Z",
      "name": "do",
      "id": "3ECf99c9842A81cA47Cd7A5380E64Fb8",
      "created_at": "1988-09-18T22:00:00.0Z",
      "host_count": 0
    },
    {
      "updated_at": "1951-09-11T23:00:00.0Z",
      "name": "a",
      "id": "97dCc7a0-95C9-3B58-b3Ca-E7ef9CE1d2F3",
      "created_at": "1994-03-31T22:00:00.0Z",
      "host_count": 20
    },
    {
      "id": "FF5d81BD-9fC7-dcA0-fEdc-5f1abAfDFc10",
      "created_at": "2002-04-20T22:00:00.0Z",
      "updated_at": "1968-05-24T23:00:00.0Z",
      "name": "sed aliqua id",
      "host_count": 0
    },
    {
      "name": "laboris tempor",
      "updated_at": "1943-08-23T22:00:00.0Z",
      "created_at": "2001-01-28T23:00:00.0Z",
      "id": "da23F7B06DA2A52e670e9d162cC03F62",
      "host_count": 20
    },
    {
      "id": "89a07eC7-C6Ed-2Fc7-D414-7518f6169D03",
      "name": "in sed aliquip ullamco",
      "updated_at": "2020-04-24T22:00:00.0Z",
      "created_at": "2020-03-06T23:00:00.0Z",
      "host_count": 0
    },
    {
      "name": "Duis culpa labore incididunt",
      "updated_at": "1979-04-19T22:00:00.0Z",
      "created_at": "2017-02-12T23:00:00.0Z",
      "id": "7bdE6521-4ed6-41bc-BEf7-fD03dD7E8aeC",
      "host_count": 0
    },
    {
      "created_at": "2013-11-23T00:00:00.0Z",
      "updated_at": "2019-02-22T23:00:00.0Z",
      "id": "Be5415b9-0ecE-7DF1-f2BA-382CaBA21Fca",
      "name": "culpa dolor in ipsum",
      "host_count": 0
    },
    {
      "name": "eiusmod culpa exercitation deserunt cupidatat",
      "id": "7625Eea9De3C5f0C13f2BbA4F20196fD",
      "updated_at": "2000-10-14T00:00:00.0Z",
      "created_at": "1971-08-04T23:00:00.0Z",
      "host_count": 20
    },
    {
      "updated_at": "1949-11-14T00:00:00.0Z",
      "created_at": "1951-11-13T00:00:00.0Z",
      "id": "0042eB156eF4EA0Dcc2dbD4AF6FdC401",
      "name": "quis",
      "host_count": 0
    },
    {
      "id": "7b4BFE1F-A9AC-F7Bf-c565-dD5E4E2AD7c6",
      "name": "laboris",
      "updated_at": "2003-01-24T23:00:00.0Z",
      "created_at": "1977-05-14T23:00:00.0Z",
      "host_count": 0
    }
  ],
  "total": 60
}
