{"name": "insights.specs.Specs.ausearch_insights_client", "exec_time": 6.031990051269531e-05, "errors": [], "results": {"type": "insights.core.spec_factory.CommandOutputProvider", "object": {"rc": null, "cmd": "/usr/sbin/ausearch -i -m avc,user_avc,selinux_err,user_selinux_err -ts recent -su insights_client --input-logs", "args": null, "save_as": false, "relative_path": "insights_commands/ausearch_-i_-m_avc_user_avc_selinux_err_user_selinux_err_-ts_recent_-su_insights_client_--input-logs"}}, "ser_time": 0.01210474967956543}